aitana/__init__.py
aitana/assimilate.py
aitana/logging_config.py
aitana/ruapehu.py
aitana/tilde.py
aitana/util.py
aitana/wfs.py
aitana/whakaari.py
aitana/data/DRZ_scaled_MAVZ.csv
aitana/data/WhiteIs_Eruption_Catalogue.csv
aitana/data/lake_height_scaling.csv
aitana/data/ruapehu_rsam.csv
aitana-0.1.9.dist-info/METADATA
aitana-0.1.9.dist-info/WHEEL
aitana-0.1.9.dist-info/RECORD
